constellaxion_utils/__init__.py
constellaxion_utils/gcs/__init__.py
constellaxion_utils/gcs/tools.py
constellaxion_utils-1.0.0.dist-info/METADATA
constellaxion_utils-1.0.0.dist-info/WHEEL
constellaxion_utils-1.0.0.dist-info/top_level.txt
constellaxion_utils-1.0.0.dist-info/RECORD
