Metadata-Version: 2.1
Name: constellaxion-utils
Version: 1.0.0
Summary: The Utils package for constellaXion CLI jobs
Author: Constellaxion Technologies, Inc.
Author-email: dev@constellaxion.ai
Requires-Dist: gcsfs
Requires-Dist: watchdog
